pelican/plugins/table_wrapper/__init__.py
pelican/plugins/table_wrapper/table_wrapper.py
pelican/plugins/table_wrapper/test_table_wrapper.py
pelican_table_wrapper-1.0.1.dist-info/WHEEL
pelican_table_wrapper-1.0.1.dist-info/METADATA
pelican_table_wrapper-1.0.1.dist-info/RECORD
