Metadata-Version: 2.1
Name: pelican-table-wrapper
Version: 1.0.1
Summary: Pelican plugin for wrapping table into classed div
Home-page: https://github.com/pawo1/table-wrapper
License: MIT
Keywords: pelican,plugin
Author: Pawo1
Requires-Python: >=3.6,<4.0
Classifier: Development Status :: 5 - Production/Stable
Classifier: Environment :: Console
Classifier: Framework :: Pelican
Classifier: Framework :: Pelican :: Plugins
Classifier: Intended Audience :: End Users/Desktop
Classifier: License :: OSI Approved :: MIT License
Classifier: Operating System :: OS Independent
Classifier: Programming Language :: Python :: 3
Classifier: Programming Language :: Python :: 3.6
Classifier: Programming Language :: Python :: 3.7
Classifier: Programming Language :: Python :: 3.8
Classifier: Programming Language :: Python :: 3.9
Classifier: Topic :: Internet :: WWW/HTTP
Classifier: Topic :: Software Development :: Libraries :: Python Modules
Provides-Extra: markdown
Requires-Dist: beautifulsoup4 (>=4.0.1,<5.0.0)
Requires-Dist: markdown (>=3.2.2,<4.0.0); extra == "markdown"
Requires-Dist: pelican (>=4.5,<5.0)
Project-URL: Documentation, https://docs.getpelican.com
Project-URL: Funding, https://donate.getpelican.com/
Project-URL: Issue Tracker, https://github.com/pawo1/table-wrapper/issues
Project-URL: Repository, https://github.com/pawo1/table-wrapper
